chebai/__init__.py
chebai/__main__.py
chebai/callbacks.py
chebai/cli.py
chebai/molecule.py
chebai/train.py
chebai/callbacks/__init__.py
chebai/callbacks/epoch_metrics.py
chebai/callbacks/model_checkpoint.py
chebai/callbacks/prediction_callback.py
chebai/loggers/__init__.py
chebai/loggers/custom.py
chebai/loss/__init__.py
chebai/loss/bce_weighted.py
chebai/loss/mixed.py
chebai/loss/pretraining.py
chebai/loss/semantic.py
chebai/models/__init__.py
chebai/models/base.py
chebai/models/chemberta.py
chebai/models/chemyk.py
chebai/models/electra.py
chebai/models/ffn.py
chebai/models/lnn_model.py
chebai/models/lstm.py
chebai/models/recursive.py
chebai/models/strontex.py
chebai/preprocessing/__init__.py
chebai/preprocessing/collate.py
chebai/preprocessing/collect_all.py
chebai/preprocessing/reader.py
chebai/preprocessing/structures.py
chebai/preprocessing/bin/BPE_SWJ/merges.txt
chebai/preprocessing/bin/BPE_SWJ/vocab.json
chebai/preprocessing/bin/deepsmiles_token/tokens.txt
chebai/preprocessing/bin/graph/tokens.txt
chebai/preprocessing/bin/selfies/tokens.txt
chebai/preprocessing/bin/smiles_token/tokens.txt
chebai/preprocessing/bin/smiles_token_unlabeled/tokens.txt
chebai/preprocessing/datasets/__init__.py
chebai/preprocessing/datasets/base.py
chebai/preprocessing/datasets/chebi.py
chebai/preprocessing/datasets/pubchem.py
chebai/preprocessing/datasets/tox21.py
chebai/preprocessing/migration/__init__.py
chebai/preprocessing/migration/chebi_data_migration.py
chebai/result/__init__.py
chebai/result/analyse_sem.py
chebai/result/base.py
chebai/result/classification.py
chebai/result/evaluate_predictions.py
chebai/result/generate_class_properties.py
chebai/result/molplot.py
chebai/result/prediction_json.py
chebai/result/pretraining.py
chebai/result/utils.py
chebai/trainer/CustomTrainer.py
chebai/trainer/__init__.py
chebai-1.0.2.dist-info/licenses/LICENSE
chebai-1.0.2.dist-info/METADATA
chebai-1.0.2.dist-info/WHEEL
chebai-1.0.2.dist-info/top_level.txt
chebai-1.0.2.dist-info/RECORD
