Metadata-Version: 2.4
Name: chebai
Version: 1.0.2
Summary: ChEBai is a deep learning library designed for the integration of deep learning methods with chemical ontologies, particularly ChEBI.
Author-email: MGlauer <martin.glauer@ovgu.de>
Maintainer-email: sfluegel05 <simon.fluegel@uni-osnabrueck.de>
License: AGPL-3.0
Requires-Python: <3.13,>=3.9
License-File: LICENSE
Requires-Dist: networkx
Requires-Dist: numpy
Requires-Dist: pandas
Requires-Dist: requests
Requires-Dist: scikit-learn
Requires-Dist: scipy
Requires-Dist: torch
Requires-Dist: transformers
Requires-Dist: fastobo
Requires-Dist: pysmiles==1.1.2
Requires-Dist: rdkit
Requires-Dist: selfies
Requires-Dist: lightning>=2.5
Requires-Dist: jsonargparse[signatures]>=4.17
Requires-Dist: omegaconf
Requires-Dist: deepsmiles
Requires-Dist: iterative-stratification
Requires-Dist: torchmetrics
Provides-Extra: dev
Requires-Dist: black; extra == "dev"
Requires-Dist: isort; extra == "dev"
Requires-Dist: pre-commit; extra == "dev"
Provides-Extra: plot
Requires-Dist: matplotlib; extra == "plot"
Requires-Dist: seaborn; extra == "plot"
Provides-Extra: wandb
Requires-Dist: wandb; extra == "wandb"
Dynamic: license-file
